LICENSE
MANIFEST.in
README.md
setup.cfg
setup.py
develop/__init__.py
develop/__main__.py
develop/checks.py
develop/config.py
develop/cycles.py
develop/execution.py
develop/git.py
develop/program.py
rapydo_develop.egg-info/PKG-INFO
rapydo_develop.egg-info/SOURCES.txt
rapydo_develop.egg-info/dependency_links.txt
rapydo_develop.egg-info/entry_points.txt
rapydo_develop.egg-info/requires.txt
rapydo_develop.egg-info/top_level.txt