Metadata-Version: 1.1
Name: rapydo-develop
Version: 0.6.1
Summary: Develop new features on RAPyDo framework
Home-page: https://rapydo.github.io/develop
Author: Paolo D'Onorio De Meo
Author-email: p.donorio.de.meo@gmail.com
License: UNKNOWN
Keywords: utilities,rapydo,logs,tools
Platform: UNKNOWN
Classifier: Programming Language :: Python
Classifier: Intended Audience :: Developers
Classifier: Development Status :: 3 - Alpha
Classifier: License :: OSI Approved :: MIT License
Classifier: Programming Language :: Python :: 3.4
Classifier: Programming Language :: Python :: 3.5
Classifier: Programming Language :: Python :: 3.6
